funcgen/__init__.py
funcgen/__version__.py
funcgen/main.py
funcgen-0.0.1.dist-info/LICENSE
funcgen-0.0.1.dist-info/METADATA
funcgen-0.0.1.dist-info/WHEEL
funcgen-0.0.1.dist-info/top_level.txt
funcgen-0.0.1.dist-info/RECORD
