Metadata-Version: 2.1
Name: funcgen
Version: 0.0.1
Summary: A small module for generating sets of function signatures and corresponding function objects.
Home-page: UNKNOWN
Author: Conrad Bailey
Author-email: conrad@cbailey.tech
License: MIT
Project-URL: Documentation, https://funcgen.readthedocs.io/en/latest/
Project-URL: Source, https://github.com/ConradBailey/funcgen
Platform: UNKNOWN
Requires-Python: >=3.6
Provides-Extra: dev
Requires-Dist: twine (==2.0.0) ; extra == 'dev'
Provides-Extra: docs
Requires-Dist: sphinx (==2.2.0) ; extra == 'docs'
